ReSubPlot/__init__.py
ReSubPlot/__main__.py
ReSubPlot/_version.py
ReSubPlot/layout.py
ReSubPlot/legends.py
ReSubPlot/master_toml.py
ReSubPlot/plotting_funcs.py
ReSubPlot/resubplot_cli.py
resubplot-1.0.1.dist-info/licenses/LICENSE
resubplot-1.0.1.dist-info/METADATA
resubplot-1.0.1.dist-info/WHEEL
resubplot-1.0.1.dist-info/entry_points.txt
resubplot-1.0.1.dist-info/top_level.txt
resubplot-1.0.1.dist-info/RECORD
