Metadata-Version: 2.4
Name: ReSubPlot
Version: 1.0.1
Summary: ReSubPlot (Replot figures to SubPlots): Plot one or many existing figure objects into a subplots() and manage labels, titles, legends, alignments, etc.
Author-email: Victor Pozsgay <victor.pozsgay@carleton.ca>
License: GNU GENERAL PUBLIC LICENSE
Project-URL: Homepage, https://github.com/VictorPozsgay/ReSubPlot
Classifier: Programming Language :: Python :: 3
Classifier: License :: OSI Approved :: GNU General Public License v3 (GPLv3)
Classifier: Operating System :: POSIX :: Linux
Classifier: Topic :: Scientific/Engineering :: GIS
Classifier: Topic :: Scientific/Engineering :: Atmospheric Science
Requires-Python: >=3.7
License-File: LICENSE
Dynamic: license-file
